amocrm/__init__.py
amocrm/api/__init__.py
amocrm/api/api_loader_amocrm_v2.py
amocrm/api/api_loader_amocrm_v4.py
amocrm/api/auth/__init__.py
amocrm/api/auth/oauth_client.py
amocrm/api/base/__init__.py
amocrm/api/base/api_loader_base.py
amocrm/config_reader/__init__.py
amocrm/config_reader/read_config.py
amocrm/db/__init__.py
amocrm/db/clickhouse_uploader.py
amocrm/db/vertica_uploader.py
amocrm/db/base/__init__.py
amocrm/db/base/uploader.py
amocrm/runner/__init__.py
amocrm/runner/runner.py
amocrm_talenttech_oss-0.4.1.dist-info/LICENSE.txt
amocrm_talenttech_oss-0.4.1.dist-info/METADATA
amocrm_talenttech_oss-0.4.1.dist-info/WHEEL
amocrm_talenttech_oss-0.4.1.dist-info/top_level.txt
amocrm_talenttech_oss-0.4.1.dist-info/RECORD
