Metadata-Version: 2.1
Name: amocrm-talenttech-oss
Version: 0.4.1
Summary: Library for retrieving and uploading to database data from amocrm API
Home-page: https://github.com/severgroup-tt/topmind-commons/tree/master/py/amocrm
Author: Dmitry Utiralov
Author-email: d.utiralov@talenttech.ru
License: MIT
Classifier: Programming Language :: Python :: 3
Classifier: License :: OSI Approved :: MIT License
Classifier: Operating System :: OS Independent
Requires-Python: >=3.6
License-File: LICENSE.txt
Requires-Dist: pandas (==1.2.4)
Requires-Dist: etl-helper-talenttech
Requires-Dist: s3-talenttech-oss (==0.0.8)
Requires-Dist: swap-inserter-talenttech-oss (==0.0.4)
Requires-Dist: clickhouse-balanced-talenttech-oss (==0.0.1)
Requires-Dist: requests
Requires-Dist: vertica-connector-talenttech (==1.2.0)
